wxyz/datagrid/__init__.py
wxyz/datagrid/_version.py
wxyz/datagrid/base.py
wxyz/datagrid/install.json
wxyz/datagrid/widget_datagrid.py
wxyz/datagrid/widget_selectgrid.py
wxyz/datagrid/widget_stylegrid.py
wxyz/datagrid/js/LICENSE.txt
wxyz/datagrid/js/README.md
wxyz/datagrid/js/package.json
wxyz/datagrid/labextension/package.json
wxyz/datagrid/labextension/static/330.e48ee1dd6d91d7d79156.js
wxyz/datagrid/labextension/static/333.c991d332dbba50320f14.js
wxyz/datagrid/labextension/static/568.4f3866bb39a91e2ed040.js
wxyz/datagrid/labextension/static/remoteEntry.6092c3fd4ac2bf1f6a32.js
wxyz/datagrid/labextension/static/style.js
wxyz_datagrid-0.5.1.data/data/share/jupyter/labextensions/@deathbeds/wxyz-datagrid/install.json
wxyz_datagrid-0.5.1.data/data/share/jupyter/labextensions/@deathbeds/wxyz-datagrid/package.json
wxyz_datagrid-0.5.1.data/data/share/jupyter/labextensions/@deathbeds/wxyz-datagrid/static/330.e48ee1dd6d91d7d79156.js
wxyz_datagrid-0.5.1.data/data/share/jupyter/labextensions/@deathbeds/wxyz-datagrid/static/333.c991d332dbba50320f14.js
wxyz_datagrid-0.5.1.data/data/share/jupyter/labextensions/@deathbeds/wxyz-datagrid/static/568.4f3866bb39a91e2ed040.js
wxyz_datagrid-0.5.1.data/data/share/jupyter/labextensions/@deathbeds/wxyz-datagrid/static/remoteEntry.6092c3fd4ac2bf1f6a32.js
wxyz_datagrid-0.5.1.data/data/share/jupyter/labextensions/@deathbeds/wxyz-datagrid/static/style.js
wxyz_datagrid-0.5.1.dist-info/LICENSE.txt
wxyz_datagrid-0.5.1.dist-info/METADATA
wxyz_datagrid-0.5.1.dist-info/WHEEL
wxyz_datagrid-0.5.1.dist-info/top_level.txt
wxyz_datagrid-0.5.1.dist-info/RECORD
